COPYRIGHT.txt
LICENSE.txt
bootstrap.py
buildout.cfg
setup.py
versions.cfg
docs/HISTORY.txt
src/megrok/__init__.py
src/megrok.resource.egg-info/PKG-INFO
src/megrok.resource.egg-info/SOURCES.txt
src/megrok.resource.egg-info/dependency_links.txt
src/megrok.resource.egg-info/namespace_packages.txt
src/megrok.resource.egg-info/not-zip-safe
src/megrok.resource.egg-info/requires.txt
src/megrok.resource.egg-info/top_level.txt
src/megrok/resource/README.txt
src/megrok/resource/__init__.py
src/megrok/resource/components.py
src/megrok/resource/configure.zcml
src/megrok/resource/directives.py
src/megrok/resource/event.py
src/megrok/resource/interfaces.py
src/megrok/resource/meta.py
src/megrok/resource/url.py
src/megrok/resource/utils.py
src/megrok/resource/ftests/__init__.py
src/megrok/resource/ftests/ftesting.zcml
src/megrok/resource/ftests/test_general.py
src/megrok/resource/ftests/css/a.js
src/megrok/resource/ftests/css/b.css
src/megrok/resource/ftests/css/b.js