Metadata-Version: 1.0
Name: megrok.resource
Version: 0.5
Summary: Grok Resources based on hurry.resource
Home-page: http://pypi.python.org/pypi/megrok.resource
Author: Souheil Chelfouh
Author-email: trollfot@gmail.com
License: ZPL 2.1
Keywords: Grok Resources
Platform: UNKNOWN
Classifier: Programming Language :: Python
Classifier: Topic :: Software Development :: Libraries :: Python Modules
Classifier: License :: OSI Approved :: Zope Public License
